{
  "project_info": {
    "project_number": "1086301440972",
    "firebase_url": "https://nirmal-bakery-a3124.firebaseio.com",
    "project_id": "nirmal-bakery-a3124",
    "storage_bucket": "nirmal-bakery-a3124.appspot.com"
  },
  "client": [
    {
      "client_info": {
        "mobilesdk_app_id": "1:1086301440972:android:7d4d95f31fb8eced282b69",
        "android_client_info": {
          "package_name": "com.example.androideatitv2server"
        }
      },
      "oauth_client": [
        {
          "client_id": "1086301440972-mr1tk6mhdob11uii5fs9mdikafjtlu90.apps.googleusercontent.com",
          "client_type": 1,
          "android_info": {
            "package_name": "com.example.androideatitv2server",
            "certificate_hash": "65553e401dde2aa5e0f181c14e8619d0af9737c3"
          }
        },
        {
          "client_id": "1086301440972-h2pqq6ijapk1pskrsth3cgrfg7kj6q73.apps.googleusercontent.com",
          "client_type": 3
        }
      ],
      "api_key": [
        {
          "current_key": "AIzaSyB64cCfLbH-OkFHLYwAq_P343mdsvdhzHA"
        }
      ],
      "services": {
        "appinvite_service": {
          "other_platform_oauth_client": [
            {
              "client_id": "1086301440972-h2pqq6ijapk1pskrsth3cgrfg7kj6q73.apps.googleusercontent.com",
              "client_type": 3
            }
          ]
        }
      }
    },
    {
      "client_info": {
        "mobilesdk_app_id": "1:1086301440972:android:1f481066933c462b282b69",
        "android_client_info": {
          "package_name": "com.example.androideatitv2shipper"
        }
      },
      "oauth_client": [
        {
          "client_id": "1086301440972-922qugcjcdp6kg0gavm3vet69131jsr7.apps.googleusercontent.com",
          "client_type": 1,
          "android_info": {
            "package_name": "com.example.androideatitv2shipper",
            "certificate_hash": "65553e401dde2aa5e0f181c14e8619d0af9737c3"
          }
        },
        {
          "client_id": "1086301440972-h2pqq6ijapk1pskrsth3cgrfg7kj6q73.apps.googleusercontent.com",
          "client_type": 3
        }
      ],
      "api_key": [
        {
          "current_key": "AIzaSyB64cCfLbH-OkFHLYwAq_P343mdsvdhzHA"
        }
      ],
      "services": {
        "appinvite_service": {
          "other_platform_oauth_client": [
            {
              "client_id": "1086301440972-h2pqq6ijapk1pskrsth3cgrfg7kj6q73.apps.googleusercontent.com",
              "client_type": 3
            }
          ]
        }
      }
    },
    {
      "client_info": {
        "mobilesdk_app_id": "1:1086301440972:android:37c16aa668d6a7c2282b69",
        "android_client_info": {
          "package_name": "com.nbfinal.androideatitv2client"
        }
      },
      "oauth_client": [
        {
          "client_id": "1086301440972-0dv0ivoe57olv9rs4d4rthdrgrlrostk.apps.googleusercontent.com",
          "client_type": 1,
          "android_info": {
            "package_name": "com.nbfinal.androideatitv2client",
            "certificate_hash": "65553e401dde2aa5e0f181c14e8619d0af9737c3"
          }
        },
        {
          "client_id": "1086301440972-h2pqq6ijapk1pskrsth3cgrfg7kj6q73.apps.googleusercontent.com",
          "client_type": 3
        }
      ],
      "api_key": [
        {
          "current_key": "AIzaSyB64cCfLbH-OkFHLYwAq_P343mdsvdhzHA"
        }
      ],
      "services": {
        "appinvite_service": {
          "other_platform_oauth_client": [
            {
              "client_id": "1086301440972-h2pqq6ijapk1pskrsth3cgrfg7kj6q73.apps.googleusercontent.com",
              "client_type": 3
            }
          ]
        }
      }
    }
  ],
  "configuration_version": "1"
}